dlt/__init__.py
dlt/api.py
dlt/helpers.py
databricks_dlt-0.3.0.dist-info/LICENSE.md
databricks_dlt-0.3.0.dist-info/METADATA
databricks_dlt-0.3.0.dist-info/NOTICE.md
databricks_dlt-0.3.0.dist-info/WHEEL
databricks_dlt-0.3.0.dist-info/top_level.txt
databricks_dlt-0.3.0.dist-info/RECORD
