Metadata-Version: 2.1
Name: databricks-dlt
Version: 0.3.0
Summary: Databricks DLT Library
Home-page: UNKNOWN
Author: Databricks
Author-email: feedback@databricks.com
License: Databricks Proprietary License
Platform: UNKNOWN
Requires-Python: >=3.9
License-File: LICENSE.md
License-File: NOTICE.md
